requirements.txt
setup.py
django_postgres_model_constraints/__init__.py
django_postgres_model_constraints/utils.py
django_postgres_model_constraints.egg-info/PKG-INFO
django_postgres_model_constraints.egg-info/SOURCES.txt
django_postgres_model_constraints.egg-info/dependency_links.txt
django_postgres_model_constraints.egg-info/requires.txt
django_postgres_model_constraints.egg-info/top_level.txt
django_postgres_model_constraints/management/__init__.py
django_postgres_model_constraints/management/commands/__init__.py
django_postgres_model_constraints/management/commands/print_model_add_foreign_key_constraint_statements.py
django_postgres_model_constraints/management/commands/print_model_add_unique_constraint_statements.py
django_postgres_model_constraints/management/commands/print_model_drop_foreign_key_constraint_statements.py
django_postgres_model_constraints/management/commands/print_model_drop_unique_constraint_statements.py