Metadata-Version: 2.1
Name: django-postgres-model-constraints
Version: 2020.7.1
Summary: django postgres model add/drop constraints statements
Home-page: https://github.com/andrewp-as-is/django-postgres-model-constraints.py
License: Unlicense
Keywords: django postgres constraints
Platform: UNKNOWN
Classifier: Framework :: Django
Classifier: License :: Public Domain
Classifier: Operating System :: OS Independent
Classifier: Programming Language :: Python :: 3
